d3net/__init__.py
d3net/args.py
d3net/comm.py
d3net/d3net_basic_blocks.py
d3net/data.py
d3net/eval.py
d3net/filter.py
d3net/lr_scheduler.py
d3net/model.py
d3net/model_openvino.py
d3net/separate.py
d3net/separate_with_openvino.py
d3net/train.py
d3net/util.py
d3net_spleeterweb-0.1.3.dist-info/METADATA
d3net_spleeterweb-0.1.3.dist-info/WHEEL
d3net_spleeterweb-0.1.3.dist-info/top_level.txt
d3net_spleeterweb-0.1.3.dist-info/RECORD
