Metadata-Version: 2.1
Name: d3net-spleeterweb
Version: 0.1.3
Summary: Unofficial Python package of D3Net implementation by Sony Research AI, used in Spleeter Web.
Home-page: https://github.com/JeffreyCA/spleeterweb-d3net
Author: JeffreyCA
Author-email: jeffreyca16@gmail.com
License: UNKNOWN
Platform: UNKNOWN
Classifier: Programming Language :: Python :: 3
Classifier: License :: OSI Approved :: Apache Software License
Classifier: Operating System :: OS Independent
Requires-Python: >=3.6
Requires-Dist: lameenc (>=1.2.2)
Requires-Dist: musdb (>=0.3.1)
Requires-Dist: museval (>=0.3.0)
Requires-Dist: requests (>=2.22)
Requires-Dist: scipy (>=1.3.1)
Requires-Dist: setuptools (>=41.0.0)
Requires-Dist: norbert (>=0.2.1)
Requires-Dist: resampy (>=0.2.2)
Requires-Dist: nnabla (>=1.13.0)
Requires-Dist: pydub (>=0.25.1)
Requires-Dist: librosa (>=0.8.0)
